py3adf-0.1.2.data/scripts/py3adf.py
py3adfslib/ADFSlib.py
py3adfslib/__init__.py
py3adf-0.1.2.dist-info/COPYING
py3adf-0.1.2.dist-info/METADATA
py3adf-0.1.2.dist-info/WHEEL
py3adf-0.1.2.dist-info/top_level.txt
py3adf-0.1.2.dist-info/RECORD
