Metadata-Version: 2.1
Name: py3adf
Version: 0.1.2
Summary: Python 3 port of ADF2INF from David Boddie's Acorn-Format-Tools.
Home-page: https://github.com/jarpy/Acorn-Format-Tools
Author: David Boddie, Toby McLaughlin
Author-email: toby@jarpy.net
License: UNKNOWN
Platform: UNKNOWN
Classifier: Development Status :: 3 - Alpha
Classifier: Environment :: Console
Classifier: Intended Audience :: End Users/Desktop
Classifier: License :: OSI Approved :: GNU General Public License v3 (GPLv3)
Classifier: Natural Language :: English
Classifier: Operating System :: OS Independent
Classifier: Programming Language :: Python :: 3
Classifier: Programming Language :: Python :: 3.7
Classifier: Programming Language :: Python :: 3.8
Requires-Python: >=3.7
